sweights/__init__.py
sweights/covariance.py
sweights/cow.py
sweights/experimental.py
sweights/independence.py
sweights/sweight.py
sweights/testing.py
sweights/typing.py
sweights/util.py
sweights-1.7.0.dist-info/LICENSE
sweights-1.7.0.dist-info/METADATA
sweights-1.7.0.dist-info/WHEEL
sweights-1.7.0.dist-info/top_level.txt
sweights-1.7.0.dist-info/RECORD
