Metadata-Version: 2.2
Name: sweights
Version: 1.7.0
Summary: Tools for producing sweights using classic methods or custom orthogonal weight functions (COWs) and for correcting covariance matrices for weighted data fits.
Author-email: Matthew Kenzie <matthew.kenzie@cern.ch>, Hans Dembinski <hans.dembinski@gmail.com>
License: MIT
Project-URL: repositoy, https://github.com/sweights/sweights
Classifier: Development Status :: 4 - Beta
Classifier: Programming Language :: Python :: 3
Classifier: Programming Language :: Python :: 3 :: Only
Classifier: License :: OSI Approved :: MIT License
Classifier: Operating System :: OS Independent
Classifier: Intended Audience :: Science/Research
Requires-Python: >=3.9
License-File: LICENSE
Requires-Dist: numpy>=1.20.1
Requires-Dist: scipy>=1.5.1
Requires-Dist: iminuit>=2.20
Provides-Extra: test
Requires-Dist: pytest; extra == "test"
Requires-Dist: pytest-xdist; extra == "test"
Requires-Dist: pytest-cov; extra == "test"
Requires-Dist: coverage[toml]; extra == "test"
Requires-Dist: matplotlib==3.9.0; extra == "test"
Provides-Extra: doc
Requires-Dist: ipython; extra == "doc"
Requires-Dist: nbsphinx; extra == "doc"
Requires-Dist: sphinx<=8.1.3; extra == "doc"
Requires-Dist: sphinx_rtd_theme; extra == "doc"
Requires-Dist: boost-histogram; extra == "doc"
Requires-Dist: matplotlib==3.9.0; extra == "doc"
Requires-Dist: uproot; extra == "doc"
Requires-Dist: pandas; extra == "doc"
Requires-Dist: resample; extra == "doc"
